cpp/__init__.py
c_py_py-0.1.5.dist-info/WHEEL
c_py_py-0.1.5.dist-info/METADATA
c_py_py-0.1.5.dist-info/RECORD
