Metadata-Version: 2.1
Name: c-py-py
Version: 0.1.5
Summary: 
License: MIT
Author: torshepherd
Author-email: tor.aksel.shepherd@gmail.com
Requires-Python: >=3.11,<4.0
Classifier: Development Status :: 4 - Beta
Classifier: Intended Audience :: Developers
Classifier: License :: OSI Approved :: MIT License
Classifier: Operating System :: OS Independent
Classifier: Programming Language :: Python
Classifier: Programming Language :: Python :: 3
Classifier: Programming Language :: Python :: 3.7
Classifier: Programming Language :: Python :: 3.8
Classifier: Programming Language :: Python :: 3.9
Classifier: Topic :: Software Development :: Libraries :: Python Modules
Requires-Dist: invoke-iife (>=1.1.0,<2.0.0)
Requires-Dist: typing-extensions (>=4.3.0,<5.0.0)
